ripio/__init__.py
ripio/core.py
ripio/exceptions/auth.py
ripio/exceptions/request.py
ripio/exceptions/response.py
ripio/trade/__init__.py
ripio/trade/client.py
ripio_client-0.0.3.dist-info/METADATA
ripio_client-0.0.3.dist-info/WHEEL
ripio_client-0.0.3.dist-info/licenses/LICENSE
ripio_client-0.0.3.dist-info/RECORD
