Metadata-Version: 2.1
Name: ripio-client
Version: 0.0.3
Summary: Ripio Client for Python
Project-URL: Homepage, https://github.com/ripio/ripio-client-python
Project-URL: Bug Tracker, https://github.com/ripio/ripio-client-python/issues
Author-email: Sebastian Serrano <sebastian@ripio.com>
License-File: LICENSE
Classifier: License :: OSI Approved :: Apache Software License
Classifier: Operating System :: OS Independent
Classifier: Programming Language :: Python :: 3
Requires-Python: >=3.7
Requires-Dist: requests>=2.28.0
